surveymonty/VERSION
surveymonty/__init__.py
surveymonty/client.py
surveymonty/constants.py
surveymonty/exceptions.py
surveymonty/utils.py
surveymonty/versions/__init__.py
surveymonty/versions/v3.json
surveymonty-0.2.5.dist-info/DESCRIPTION.rst
surveymonty-0.2.5.dist-info/METADATA
surveymonty-0.2.5.dist-info/RECORD
surveymonty-0.2.5.dist-info/WHEEL
surveymonty-0.2.5.dist-info/metadata.json
surveymonty-0.2.5.dist-info/top_level.txt
tests/__init__.py
tests/integration/__init__.py
tests/integration/test_api.py
tests/unit/__init__.py
tests/unit/test_client.py
tests/unit/test_utils.py
