Metadata-Version: 2.0
Name: surveymonty
Version: 0.2.5
Summary: Python wrapper for SurveyMonkey API
Home-page: https://github.com/andrewkshim/SurveyMonty
Author: Andrew Shim
Author-email: andrewkshim92@gmail.com
License: MIT
Keywords: SurveyMonkey
Platform: UNKNOWN
Requires-Dist: requests (>=2.12.4,<3.0)
